{
  "$schema": "./node_modules/nx/schemas/workspace-schema.json",
  "version": 2,
  "projects": {
    "api-interfaces": "libs/api-interfaces",
    "asset-price-api": "apps/asset-price-api",
    "auth0": "libs/auth0",
    "collateral-api": "apps/collateral-api",
    "config": "libs/config",
    "credit-api": "apps/credit-api",
    "crypto": "libs/crypto",
    "health": "libs/health",
    "internal-api": "libs/internal-api",
    "onboarding-api": "apps/onboarding-api",
    "openapi": "libs/openapi",
    "plugin-deployment": "libs/plugin-deployment",
    "referral-system-api": "apps/referral-system-api",
    "sendgrid": "libs/sendgrid",
    "user-api": "apps/user-api",
    "vault": "libs/vault"
  }
}
